Workbook

Sheet Assumptions
A1: ROBOFOLIO — Business Case Assumptions
A3: KOMMISSIONSMODELL
A4: Kommission pro Transaktion | B4: 0.0375
A5: Ø Transaktionswert (Deal Size) | B5: 75000
A6: Ø Kommission pro Deal | B6: =B4*B5 -> 2812.5
A8: MARKT & WACHSTUM
A9: Adressierbarer Markt DE (KMU Hersteller) | B9: 50000
A10: Davon automatisierungsbereit (TAM %) | B10: 0.15
A11: TAM (Anzahl Unternehmen) | B11: =B9*B10 -> 7500
A12: Conversion Rate (Lead → Deal) | B12: 0.08
A14: PLATTFORM-WACHSTUM (Deals/Monat)
A15: Jahr 1 — Deals/Monat (Start → Ende) | B15: 2 | C15: 5
A16: Jahr 2 — Deals/Monat (Start → Ende) | B16: 5 | C16: 12
A17: Jahr 3 — Deals/Monat (Start → Ende) | B17: 12 | C17: 25
A18: Jahr 4 — Deals/Monat (Start → Ende) | B18: 25 | C18: 40
A19: Jahr 5 — Deals/Monat (Start → Ende) | B19: 40 | C19: 60
A21: KOSTEN
A22: Gründer-Gehälter (2 Personen, p.a.) | B22: 0
A23: Hosting & Infrastruktur (p.a. Start) | B23: 3600
A24: Anthropic API Kosten (p.a. Start) | B24: 2400
A25: Marketing & Vertrieb (p.a. Start) | B25: 12000
A26: Rechts & Buchhaltung (p.a.) | B26: 6000
A27: Sonstige Kosten (p.a. Start) | B27: 3000
A28: Kostenwachstum p.a. (Infrastruktur/API/Marketing) | B28: 0.3

Sheet P&L Projektion
B1: Jahr 1 | C1: Jahr 2 | D1: Jahr 3 | E1: Jahr 4 | F1: Jahr 5 | G1: Gesamt
A3: UMSATZ (Revenue)
A4: Ø Deals/Monat | B4: =AVERAGE(Assumptions!B15,Assumptions!C15) -> 3.5 | C4: =AVERAGE(Assumptions!B16,Assumptions!C16) -> 8.5 | D4: =AVERAGE(Assumptions!B17,Assumptions!C17) -> 18.5 | E4: =AVERAGE(Assumptions!B18,Assumptions!C18) -> 32.5 | F4: =AVERAGE(Assumptions!B19,Assumptions!C19) -> 50
A5: Deals/Jahr | B5: =B4*12 -> 42 | C5: =C4*12 -> 102 | D5: =D4*12 -> 222 | E5: =E4*12 -> 390 | F5: =F4*12 -> 600 | G5: =SUM(B5:F5) -> 1356
A6: Ø Transaktionswert | B6: =Assumptions!B5 -> 75000 | C6: =Assumptions!B5 -> 75000 | D6: =Assumptions!B5 -> 75000 | E6: =Assumptions!B5 -> 75000 | F6: =Assumptions!B5 -> 75000
A7: Transaktionsvolumen (GMV) | B7: =B5*B6 -> 3150000 | C7: =C5*C6 -> 7650000 | D7: =D5*D6 -> 16650000 | E7: =E5*E6 -> 29250000 | F7: =F5*F6 -> 45000000 | G7: =SUM(B7:F7) -> 101700000
A8: Kommissionssatz | B8: =Assumptions!B4 -> 0.0375 | C8: =Assumptions!B4 -> 0.0375 | D8: =Assumptions!B4 -> 0.0375 | E8: =Assumptions!B4 -> 0.0375 | F8: =Assumptions!B4 -> 0.0375
A9: UMSATZ (Kommissionserlöse) | B9: =B7*B8 -> 118125 | C9: =C7*C8 -> 286875 | D9: =D7*D8 -> 624375 | E9: =E7*E8 -> 1096875 | F9: =F7*F8 -> 1687500 | G9: =SUM(B9:F9) -> 3813750
A11: KOSTEN (Expenses)
A12: Gründer-Gehälter | B12: =Assumptions!B22 -> 0 | C12: =Assumptions!B22 -> 0 | D12: =Assumptions!B22 -> 0 | E12: =Assumptions!B22 -> 0 | F12: =Assumptions!B22 -> 0
A13: Hosting & Infrastruktur | B13: =Assumptions!B23 -> 3600 | C13: =B13*(1+Assumptions!$B$28) -> 4680 | D13: =C13*(1+Assumptions!$B$28) -> 6084 | E13: =D13*(1+Assumptions!$B$28) -> 7909.2 | F13: =E13*(1+Assumptions!$B$28) -> 10281.96
A14: Anthropic API Kosten | B14: =Assumptions!B24 -> 2400 | C14: =B14*(1+Assumptions!$B$28) -> 3120 | D14: =C14*(1+Assumptions!$B$28) -> 4056 | E14: =D14*(1+Assumptions!$B$28) -> 5272.8 | F14: =E14*(1+Assumptions!$B$28) -> 6854.64
A15: Marketing & Vertrieb | B15: =Assumptions!B25 -> 12000 | C15: =B15*(1+Assumptions!$B$28) -> 15600 | D15: =C15*(1+Assumptions!$B$28) -> 20280 | E15: =D15*(1+Assumptions!$B$28) -> 26364 | F15: =E15*(1+Assumptions!$B$28) -> 34273.2
A16: Rechts & Buchhaltung | B16: =Assumptions!B26 -> 6000 | C16: =Assumptions!B26 -> 6000 | D16: =Assumptions!B26 -> 6000 | E16: =Assumptions!B26 -> 6000 | F16: =Assumptions!B26 -> 6000
A17: Sonstige Kosten | B17: =Assumptions!B27 -> 3000 | C17: =B17*(1+Assumptions!$B$28) -> 3900 | D17: =C17*(1+Assumptions!$B$28) -> 5070 | E17: =D17*(1+Assumptions!$B$28) -> 6591 | F17: =E17*(1+Assumptions!$B$28) -> 8568.3
A18: GESAMTKOSTEN | B18: =SUM(B12:B17) -> 27000 | C18: =SUM(C12:C17) -> 33300 | D18: =SUM(D12:D17) -> 41490 | E18: =SUM(E12:E17) -> 52137 | F18: =SUM(F12:F17) -> 65978.1 | G18: =SUM(B18:F18) -> 219905.1
A20: ERGEBNIS (Profit)
A21: EBIT (Gewinn/Verlust) | B21: =B9-B18 -> 91125 | C21: =C9-C18 -> 253575 | D21: =D9-D18 -> 582885 | E21: =E9-E18 -> 1044738 | F21: =F9-F18 -> 1621521.9 | G21: =SUM(B21:F21) -> 3593844.9
A22: EBIT-Marge | B22: =IF(B9=0,0,B21/B9) -> 0.77142857 | C22: =IF(C9=0,0,C21/C9) -> 0.88392157 | D22: =IF(D9=0,0,D21/D9) -> 0.93354955 | E22: =IF(E9=0,0,E21/E9) -> 0.95246769 | F22: =IF(F9=0,0,F21/F9) -> 0.96090187
A23: Kumulierter Gewinn/Verlust | B23: =B21 -> 91125 | C23: =B23+C21 -> 344700 | D23: =C23+D21 -> 927585 | E23: =D23+E21 -> 1972323 | F23: =E23+F21 -> 3593844.9
A25: KEY METRICS
A26: Ø Kommission pro Deal | B26: =Assumptions!B6 -> 2812.5 | C26: =Assumptions!B6 -> 2812.5 | D26: =Assumptions!B6 -> 2812.5 | E26: =Assumptions!B6 -> 2812.5 | F26: =Assumptions!B6 -> 2812.5
A27: Break-Even Deals/Monat | B27: =IF(Assumptions!B6=0,0,ROUNDUP(B18/12/Assumptions!B6,0)) -> 1 | C27: =IF(Assumptions!B6=0,0,ROUNDUP(C18/12/Assumptions!B6,0)) -> 1 | D27: =IF(Assumptions!B6=0,0,ROUNDUP(D18/12/Assumptions!B6,0)) -> 2 | E27: =IF(Assumptions!B6=0,0,ROUNDUP(E18/12/Assumptions!B6,0)) -> 2 | F27: =IF(Assumptions!B6=0,0,ROUNDUP(F18/12/Assumptions!B6,0)) -> 2
A28: Umsatz pro Monat (Ø) | B28: =B9/12 -> 9843.75 | C28: =C9/12 -> 23906.25 | D28: =D9/12 -> 52031.25 | E28: =E9/12 -> 91406.25 | F28: =F9/12 -> 140625

Sheet Szenarien
B1: Conservative | C1: Base Case | D1: Optimistic
A3: ANNAHMEN
A4: Ø Deal Size | B4: 50000 | C4: 75000 | D4: 100000
A5: Deals/Monat Jahr 5 | B5: 35 | C5: 60 | D5: 90
A6: Kommissionssatz | B6: 0.0375 | C6: 0.0375 | D6: 0.0375
A8: ERGEBNIS JAHR 5
A9: Deals/Jahr | B9: =B5*12 -> 420 | C9: =C5*12 -> 720 | D9: =D5*12 -> 1080
A10: GMV (Transaktionsvolumen) | B10: =B9*B4 -> 21000000 | C10: =C9*C4 -> 54000000 | D10: =D9*D4 -> 108000000
A11: Jahresumsatz (Kommissionen) | B11: =B10*B6 -> 787500 | C11: =C10*C6 -> 2025000 | D11: =D10*D6 -> 4050000
A12: Monatsumsatz (Ø) | B12: =B11/12 -> 65625 | C12: =C11/12 -> 168750 | D12: =D11/12 -> 337500
A14: 5-JAHRES KUMULIERT
A15: Geschätzte Deals gesamt (5J) | B15: 90 | C15: 125 | D15: 175
A16: Kumulierter GMV (5J) | B16: =B15*B4 -> 4500000 | C16: =C15*C4 -> 9375000 | D16: =D15*D4 -> 17500000
A17: Kumulierter Umsatz (5J) | B17: =B16*B6 -> 168750 | C17: =C16*C6 -> 351562.5 | D17: =D16*D6 -> 656250
